{
    "os": "Windows-10-10.0.19041-SP0",
    "python": "3.8.1",
    "heartbeatAt": "2023-06-05T18:03:48.541274",
    "startedAt": "2023-06-05T18:03:48.072992",
    "docker": null,
    "cuda": null,
    "args": [],
    "state": "running",
    "program": "G:/Work/mcgill/metro/forecastable/exps/ABtransformer/MCR02self_supervised_v.py",
    "codePath": "exps\\ABtransformer\\MCR02self_supervised_v.py",
    "git": {
        "remote": "https://github.com/chengzhanhong/forecastable.git",
        "commit": "2cf941c75488bcb7386357e38a6fb061c49b5e2b"
    },
    "email": null,
    "root": "G:/Work/mcgill/metro/forecastable",
    "host": "153SMART-07",
    "username": "jwang317",
    "executable": "C:\\Users\\jwang317\\AppData\\Local\\Programs\\Python\\Python38\\python.exe",
    "cpu_count": 8,
    "cpu_count_logical": 8,
    "cpu_freq": {
        "current": 3000.0,
        "min": 0.0,
        "max": 3000.0
    },
    "cpu_freq_per_core": [
        {
            "current": 3000.0,
            "min": 0.0,
            "max": 3000.0
        }
    ],
    "disk": {
        "total": 1863.0156211853027,
        "used": 160.98766326904297
    },
    "gpu": "NVIDIA GeForce RTX 2080 SUPER",
    "gpu_count": 1,
    "gpu_devices": [
        {
            "name": "NVIDIA GeForce RTX 2080 SUPER",
            "memory_total": 8589934592
        }
    ],
    "memory": {
        "total": 15.823135375976562
    }
}
